test/__init__.py
test/test_validator.py
datavalidatepro-0.1.dist-info/METADATA
datavalidatepro-0.1.dist-info/WHEEL
datavalidatepro-0.1.dist-info/top_level.txt
datavalidatepro-0.1.dist-info/RECORD
