Metadata-Version: 2.4
Name: datavalidatepro
Version: 0.1
Summary: A simple datavalidator for validating email, phone numbers, dates, and URLs.TO validate Url's, use the validate_url() methodFor that of phone numbers, use the Validate_phone() method.Also users can validate a phone_number from 6 continents by using the continentname_numbers etcFor that of emails use the Validate_email() method.Lastly,to validate dates, use the  validate_date method. Note: These methods return a boolean True if valid and False if Invalid
Home-page: https://github.com/Data-Epic/data-validator-ogechukwu-okoli
Author: Okoli Ogechukwu Abimbola
Author-email: okoliogechi74@gmail.com
Classifier: Programming Language :: Python :: 3.13
Classifier: License :: OSI Approved :: MIT License
Classifier: Operating System :: OS Independent
Requires-Python: >=3.6
Dynamic: author
Dynamic: author-email
Dynamic: classifier
Dynamic: description-content-type
Dynamic: home-page
Dynamic: requires-python
Dynamic: summary
